opencodespace/__init__.py
opencodespace/main.py
opencodespace/providers/__init__.py
opencodespace/providers/base.py
opencodespace/providers/fly.py
opencodespace/providers/local.py
opencodespace/providers/registry.py
opencodespace-0.5.0.dist-info/licenses/LICENSE
opencodespace-0.5.0.dist-info/METADATA
opencodespace-0.5.0.dist-info/WHEEL
opencodespace-0.5.0.dist-info/entry_points.txt
opencodespace-0.5.0.dist-info/top_level.txt
opencodespace-0.5.0.dist-info/RECORD
