Metadata-Version: 2.4
Name: opencodespace
Version: 0.5.0
Summary: Launch disposable VS Code development environments with AI tooling support
Home-page: https://github.com/ngramai/opencodespace
Author: ngram.com
Author-email: ngram-ai <eng@ngram.com>
License: MIT
Project-URL: Homepage, https://github.com/devadutta/opencodespace
Project-URL: Bug Reports, https://github.com/devadutta/opencodespace/issues
Project-URL: Source, https://github.com/devadutta/opencodespace
Keywords: development,vscode,docker,cloud,devops,ai
Classifier: Development Status :: 4 - Beta
Classifier: Intended Audience :: Developers
Classifier: Topic :: Software Development :: Build Tools
Classifier: License :: OSI Approved :: MIT License
Classifier: Programming Language :: Python :: 3
Classifier: Programming Language :: Python :: 3.7
Classifier: Programming Language :: Python :: 3.8
Classifier: Programming Language :: Python :: 3.9
Classifier: Programming Language :: Python :: 3.10
Classifier: Programming Language :: Python :: 3.11
Classifier: Operating System :: OS Independent
Requires-Python: >=3.7
License-File: LICENSE
Requires-Dist: click>=8.0.0
Requires-Dist: questionary>=1.10.0
Requires-Dist: toml>=0.10.2
Requires-Dist: importlib-metadata>=4.0.0; python_version < "3.8"
Requires-Dist: importlib-resources>=5.0.0; python_version < "3.9"
Dynamic: author
Dynamic: home-page
Dynamic: license-file
Dynamic: requires-python
